{
"name": "int_4027",
"children": [
{
 "name": "int_3803",
 "children": [
 {
  "name": "int_3628",
  "children": [
  {
   "name": "pt_48927",
   "category": "nettles"
  },
  {
   "name": "int_2658",
   "children": [
   {
    "name": "best_int_8",
    "children": [
    {
     "name": "pt_51565",
     "category": "swayze"
    },
    {
     "name": "pt_53595",
     "img": "http://farm1.static.flickr.com/37/79154560_06d8927520.jpg",
     "category": "kristofferson"
    }
    ]
   },
   {
    "name": "best_int_2658",
    "children": [
    {
     "name": "pt_25807",
     "img": "http://farm4.static.flickr.com/3426/3223486855_a620e2ddae.jpg",
     "category": "scarlett"
    },
    {
     "name": "pt_27487",
     "img": "http://farm3.static.flickr.com/2375/2442855068_c8874f4bb6.jpg",
     "category": "mandy"
    },
    {
     "name": "pt_28448",
     "category": "bianca"
    },
    {
     "name": "pt_32680",
     "category": "fiennes"
    },
    {
     "name": "pt_35156",
     "img": "http://www.belizex.com/images/birding/motmot.jpg",
     "category": "blanchett"
    }
    ]
   },
   {
    "name": "best_int_2053",
    "children": [
    {
     "name": "pt_23856",
     "img": "http://www.laptopsarena.com/wp-content/uploads/cebit-2008-new-asus-notebooks-showcased.jpg",
     "category": "angelina"
    },
    {
     "name": "pt_38742",
     "img": "http://www.a-zdogs.net/mini/foxtwire.jpg",
     "category": "vinnie"
    }
    ]
   }
   ]
  },
  {
   "name": "int_3025",
   "children": [
   {
    "name": "pt_39251",
    "img": "http://www.pisitoenmadrid.com/images/curiosidades/relojdearena.jpg",
    "category": "timmy"
   },
   {
    "name": "int_2804",
    "children": [
    {
     "name": "pt_34622",
     "img": "http://farm2.static.flickr.com/1237/1263352924_ad4d8f441e.jpg",
     "category": "askew"
    },
    {
     "name": "best_int_2804",
     "children": [
     {
      "name": "pt_15974",
      "img": "http://static.flickr.com/3145/2817296882_107e7a35f8.jpg",
      "category": "willy"
     },
     {
      "name": "pt_51192",
      "img": "http://farm4.static.flickr.com/3206/2858161293_1386534211.jpg",
      "category": "paulie"
     },
     {
      "name": "pt_53436",
      "img": "http://blog.makezine.com/315169808_e5a59ebc22_b.jpg",
      "category": "collard"
     },
     {
      "name": "pt_58274",
      "category": "bowser"
     },
     {
      "name": "pt_69369",
      "img": "http://farm4.static.flickr.com/3166/2449598822_fea19b51d9.jpg",
      "category": "papin"
     }
     ]
    },
    {
     "name": "best_int_1342",
     "children": [
     {
      "name": "pt_34499",
      "img": "http://farm1.static.flickr.com/7/11438354_ddbae9b5ea.jpg",
      "category": "theron"
     },
     {
      "name": "pt_45822",
      "category": "auld"
     },
     {
      "name": "pt_50776",
      "img": "http://static.flickr.com/1234/613831711_9a88c4a011.jpg",
      "category": "charlize"
     },
     {
      "name": "pt_60678",
      "img": "http://farm2.static.flickr.com/1228/570788391_857bd20da5.jpg",
      "category": "marwijk"
     }
     ]
    }
    ]
   }
   ]
  },
  {
   "name": "best_int_3628",
   "children": [
   {
    "name": "pt_21783",
    "img": "http://farm3.static.flickr.com/2264/2199720668_de2a038058.jpg",
    "category": "faye"
   },
   {
    "name": "pt_29663",
    "img": "http://www.monkeymatters.com/articles/buttons/2.jpg",
    "category": "baez"
   },
   {
    "name": "pt_37718",
    "img": "http://farm1.static.flickr.com/21/32166998_4ececdd939.jpg",
    "category": "lemaire"
   },
   {
    "name": "pt_39970",
    "category": "wooten"
   },
   {
    "name": "pt_40471",
    "category": "slay"
   }
   ]
  }
  ]
 },
 {
  "name": "best_int_3803",
  "children": [
  {
   "name": "pt_5285",
   "img": "http://farm2.static.flickr.com/1275/1064659349_6d11a714a9.jpg",
   "category": "johnny"
  },
  {
   "name": "pt_13079",
   "img": "http://farm2.static.flickr.com/1430/590089269_3059bff680.jpg",
   "category": "tina"
  },
  {
   "name": "pt_13286",
   "img": "http://farm1.static.flickr.com/22/30449270_c387110eb4.jpg",
   "category": "teddy"
  },
  {
   "name": "pt_13422",
   "img": "http://farm1.static.flickr.com/24/57086062_92d364b602.jpg",
   "category": "cindy"
  },
  {
   "name": "pt_15007",
   "category": "maggie"
  }
  ]
 }
 ]
},
{
 "name": "best_int_857",
 "children": [
 {
  "name": "pt_33158",
  "img": "http://farm4.static.flickr.com/3515/3780435868_c9b9629ba9.jpg",
  "category": "cassie"
 },
 {
  "name": "pt_33590",
  "category": "stepson"
 },
 {
  "name": "pt_34861",
  "img": "http://farm1.static.flickr.com/54/147729281_1b0a0c4185.jpg",
  "category": "stepdaughter"
 },
 {
  "name": "pt_40337",
  "img": "http://farm4.static.flickr.com/3074/2314045260_b3101f7281.jpg",
  "category": "ex-wife"
 },
 {
  "name": "pt_54945",
  "img": "http://farm4.static.flickr.com/3192/2507361512_b5f06ff7f1.jpg",
  "category": "ex-husband"
 }
 ]
},
{
 "name": "int_3168",
 "children": [
 {
  "name": "pt_67141",
  "category": "knopfler"
 },
 {
  "name": "best_int_806",
  "children": [
  {
   "name": "pt_60672",
   "img": "http://farm2.static.flickr.com/1133/782318635_2def9c6d48.jpg",
   "category": "rimmer"
  },
  {
   "name": "pt_69909",
   "img": "http://farm2.static.flickr.com/1370/956045634_6f14b93f91.jpg",
   "category": "deschanel"
  }
  ]
 },
 {
  "name": "best_int_3168",
  "children": [
  {
   "name": "pt_32567",
   "img": "http://farm4.static.flickr.com/3021/2337507530_da809baebe.jpg",
   "category": "dawkins"
  },
  {
   "name": "pt_33824",
   "img": "http://www.chowchows.com/images/dogs/prissy.jpg",
   "category": "connery"
  },
  {
   "name": "pt_42584",
   "img": "http://farm1.static.flickr.com/99/293262347_e65eef31b5.jpg",
   "category": "duchovny"
  },
  {
   "name": "pt_43035",
   "category": "kravitz"
  },
  {
   "name": "pt_50135",
   "img": "http://a1.phobos.apple.com/us/r30/Purple/8e/95/8f/mzl.fkgisbtt.480x480-75.jpg",
   "category": "nigh"
  }
  ]
 }
 ]
},
{
 "name": "int_3690",
 "children": [
 {
  "name": "best_int_3690",
  "children": [
  {
   "name": "pt_4785",
   "img": "http://www.mousetrax.com/PetPics/Bark2006/PICT0038.jpg",
   "category": "billy"
  },
  {
   "name": "pt_7617",
   "img": "http://farm3.static.flickr.com/2654/4090529825_72858f1298.jpg",
   "category": "kate"
  },
  {
   "name": "pt_9448",
   "img": "http://farm3.static.flickr.com/2134/1968846559_5df15e98f3.jpg",
   "category": "mickey"
  },
  {
   "name": "pt_10146",
   "img": "http://farm4.static.flickr.com/3423/3889571100_716dc089c1.jpg",
   "category": "jake"
  },
  {
   "name": "pt_10395",
   "category": "lucy"
  }
  ]
 },
 {
  "name": "int_3126",
  "children": [
  {
   "name": "best_int_3126",
   "children": [
   {
    "name": "pt_4064",
    "category": "jerry"
   },
   {
    "name": "pt_7930",
    "category": "julie"
   },
   {
    "name": "pt_8567",
    "img": "http://farm1.static.flickr.com/201/517547673_833c57f5b2.jpg",
    "category": "lou"
   },
   {
    "name": "pt_8907",
    "img": "http://farm4.static.flickr.com/3272/3119924531_e1f0c7a64d.jpg",
    "category": "jackie"
   },
   {
    "name": "pt_10833",
    "img": "http://farm4.static.flickr.com/3013/3006683029_56453f5142.jpg",
    "category": "judy"
   }
   ]
  },
  {
   "name": "best_int_2446",
   "children": [
   {
    "name": "pt_8207",
    "img": "http://www.contentparadise.com/user/providerimage.php?productid=45828&uri=/images/Mystique_/Mystique_SWG/SWG_01.jpg",
    "category": "willie"
   },
   {
    "name": "pt_47611",
    "img": "http://upload.wikimedia.org/wikipedia/commons/thumb/3/3e/Brosen_camelus_dromedarius1.jpg/180px-Brosen_camelus_dromedarius1.jpg",
    "category": "physiotherapist"
   }
   ]
  },
  {
   "name": "int_2913",
   "children": [
   {
    "name": "best_int_542",
    "children": [
    {
     "name": "pt_11956",
     "img": "http://www.pritameames.com/Osgood83AndamanPadaukChest208.jpg",
     "category": "marilyn"
    },
    {
     "name": "pt_24349",
     "category": "smiley"
    },
    {
     "name": "pt_37305",
     "category": "bessie"
    },
    {
     "name": "pt_37726",
     "img": "http://farm2.static.flickr.com/1211/1264973730_7591dcd58c.jpg",
     "category": "sadie"
    },
    {
     "name": "pt_49130",
     "img": "http://farm4.static.flickr.com/3162/2519150557_6cdbc4fe32.jpg",
     "category": "cleese"
    }
    ]
   },
   {
    "name": "best_int_2913",
    "children": [
    {
     "name": "pt_6807",
     "category": "chuck"
    },
    {
     "name": "pt_12208",
     "category": "calvin"
    },
    {
     "name": "pt_13771",
     "category": "robbins"
    },
    {
     "name": "pt_15841",
     "img": "http://i70.photobucket.com/albums/i94/gwendog/fashion/220trinaturksterlingtrenchnord.jpg",
     "category": "shelley"
    },
    {
     "name": "pt_20076",
     "category": "cassidy"
    }
    ]
   },
   {
    "name": "best_int_68",
    "children": [
    {
     "name": "pt_12270",
     "img": "http://farm4.static.flickr.com/3276/2521986486_d031b9cce9.jpg",
     "category": "jenny"
    },
    {
     "name": "pt_13354",
     "img": "http://farm1.static.flickr.com/212/469340851_26dc154b2c.jpg",
     "category": "kelley"
    },
    {
     "name": "pt_15234",
     "img": "http://farm4.static.flickr.com/3623/3505050130_44db0bff00.jpg",
     "category": "elton"
    },
    {
     "name": "pt_16985",
     "img": "http://www.cruffler.com/Features/APR-02/M1912HolsterOpen.jpg",
     "category": "crowe"
    },
    {
     "name": "pt_17530",
     "img": "http://farm3.static.flickr.com/2493/3928873419_96d067fc74.jpg",
     "category": "cathy"
    }
    ]
   }
   ]
  }
  ]
 },
 {
  "name": "int_2829",
  "children": [
  {
   "name": "best_int_2829",
   "children": [
   {
    "name": "pt_46179",
    "category": "cordelia"
   },
   {
    "name": "pt_58569",
    "category": "smothers"
   },
   {
    "name": "pt_68573",
    "category": "yoakam"
   },
   {
    "name": "pt_69443",
    "category": "comedienne"
   }
   ]
  },
  {
   "name": "best_int_2440",
   "children": [
   {
    "name": "pt_27280",
    "img": "http://farm1.static.flickr.com/66/224738264_fdbc6e9a9a.jpg",
    "category": "depp"
   },
   {
    "name": "pt_46941",
    "img": "http://farm2.static.flickr.com/1289/1400661393_06fd2199b6.jpg",
    "category": "lancelot"
   }
   ]
  },
  {
   "name": "best_int_1065",
   "children": [
   {
    "name": "pt_19898",
    "img": "http://farm1.static.flickr.com/30/35195807_744968efd0.jpg",
    "category": "stevie"
   },
   {
    "name": "pt_23712",
    "img": "http://farm1.static.flickr.com/14/15180058_e820d877b4.jpg",
    "category": "travolta"
   },
   {
    "name": "pt_48905",
    "img": "http://farm1.static.flickr.com/78/159241744_d010ac133e.jpg",
    "category": "ronstadt"
   },
   {
    "name": "pt_59751",
    "img": "http://www.northlanddistrib.com/beacon-morris/images/hydonic_heater.jpg",
    "category": "sedaris"
   },
   {
    "name": "pt_60094",
    "img": "http://farm1.static.flickr.com/46/132283263_149829c817.jpg",
    "category": "stewie"
   }
   ]
  }
  ]
 }
 ]
},
{
 "name": "best_int_4027",
 "children": [
 {
  "name": "pt_18330",
  "category": "clooney"
 },
 {
  "name": "pt_18855",
  "img": "http://www.southernplate.com/wp-content/uploads/2009/06/dscn0819-400x300.jpg",
  "category": "spector"
 },
 {
  "name": "pt_21336",
  "img": "http://farm3.static.flickr.com/2124/1798640171_e0a3034f32.jpg",
  "category": "fonda"
 },
 {
  "name": "pt_21952",
  "category": "scully"
 },
 {
  "name": "pt_22391",
  "img": "http://farm3.static.flickr.com/2117/2437659378_fea1f3358c.jpg",
  "category": "mulder"
 }
 ]
}
]
}
